{"id": "core~139549", "triplet_id": "core~master~Ia0d15eb3e235fbd750b818009b5168c61c6ff0ec", "project": "core", "branch": "master", "attention_set": {}, "removed_from_attention_set": {"1000006": {"account": {"_account_id": 1000006, "name": "Thorsten Behrens", "email": "thorsten.behrens@collabora.com", "username": "thb"}, "last_update": "2022-11-23 16:04:02.000000000", "reason": "<GERRIT_ACCOUNT_1000006> replied on the change", "reason_account": {"_account_id": 1000006, "name": "Thorsten Behrens", "email": "thorsten.behrens@collabora.com", "username": "thb"}}, "1003709": {"account": {"_account_id": 1003709, "name": "Gnil Gnay", "display_name": "Ling Yang", "email": "gnaygnil@gmail.com", "username": "gnaygnil"}, "last_update": "2023-01-24 03:19:12.000000000", "reason": "Change was abandoned"}}, "hashtags": [], "change_id": "Ia0d15eb3e235fbd750b818009b5168c61c6ff0ec", "subject": "add \"LOONGARCH64\" to the JAVAINTERPRETER 64bit check", "status": "MERGED", "created": "2022-09-07 02:29:46.000000000", "updated": "2023-01-26 16:45:19.000000000", "submitted": "2023-01-26 16:45:19.000000000", "submitter": {"_account_id": 1000022, "name": "Michael Stahl", "email": "michael.stahl@collabora.com", "username": "mst", "status": "🦥"}, "insertions": 1, "deletions": 1, "total_comment_count": 3, "unresolved_comment_count": 0, "has_review_started": true, "submission_id": "139549", "meta_rev_id": "879c4d9d79c8ef93a013425aaaa83a13706c90cb", "_number": 139549, "virtual_id_number": 139549, "owner": {"_account_id": 1003709, "name": "Gnil Gnay", "display_name": "Ling Yang", "email": "gnaygnil@gmail.com", "username": "gnaygnil"}, "labels": {"Verified": {"all": [{"value": 0, "_account_id": 1000130, "name": "René Engelhard", "email": "rene@debian.org", "username": "rene"}, {"tag": "autogenerated:gerrit:merged", "value": 1, "date": "2023-01-26 16:45:19.000000000", "permitted_voting_range": {"min": 1, "max": 1}, "_account_id": 1000855, "name": "Jenkins", "username": "ci", "tags": ["SERVICE_USER"]}, {"value": 0, "_account_id": 1000022, "name": "Michael Stahl", "email": "michael.stahl@collabora.com", "username": "mst", "status": "🦥"}, {"value": 0, "_account_id": 1003709, "name": "Gnil Gnay", "display_name": "Ling Yang", "email": "gnaygnil@gmail.com", "username": "gnaygnil"}], "values": {"-1": "Fails", " 0": "No score", "+1": "Verified"}, "default_value": 0}, "Code-Review": {"all": [{"value": 0, "_account_id": 1000130, "name": "René Engelhard", "email": "rene@debian.org", "username": "rene"}, {"value": 0, "_account_id": 1000855, "name": "Jenkins", "username": "ci", "tags": ["SERVICE_USER"]}, {"tag": "autogenerated:gerrit:merged", "value": 2, "date": "2023-01-26 16:45:19.000000000", "permitted_voting_range": {"min": 2, "max": 2}, "_account_id": 1000022, "name": "Michael Stahl", "email": "michael.stahl@collabora.com", "username": "mst", "status": "🦥"}, {"value": 0, "_account_id": 1003709, "name": "Gnil Gnay", "display_name": "Ling Yang", "email": "gnaygnil@gmail.com", "username": "gnaygnil"}], "values": {"-2": "Do not merge", "-1": "This need some tweaks before it is merged", " 0": "No score", "+1": "Looks good to me, but someone else must approve", "+2": "Looks good to me, approved"}, "default_value": 0}}, "removable_reviewers": [{"_account_id": 1000006, "name": "Thorsten Behrens", "email": "thorsten.behrens@collabora.com", "username": "thb"}], "reviewers": {"CC": [{"_account_id": 1000083, "name": "Noel Grandin", "email": "noel.grandin@collabora.co.uk", "username": "grandinj"}, {"_account_id": 1001371, "name": "Review bot", "username": "pootlebot", "status": "🤖", "tags": ["SERVICE_USER"]}], "REVIEWER": [{"_account_id": 1000006, "name": "Thorsten Behrens", "email": "thorsten.behrens@collabora.com", "username": "thb"}, {"_account_id": 1000022, "name": "Michael Stahl", "email": "michael.stahl@collabora.com", "username": "mst", "status": "🦥"}, {"_account_id": 1000130, "name": "René Engelhard", "email": "rene@debian.org", "username": "rene"}, {"_account_id": 1000855, "name": "Jenkins", "username": "ci", "tags": ["SERVICE_USER"]}, {"_account_id": 1003709, "name": "Gnil Gnay", "display_name": "Ling Yang", "email": "gnaygnil@gmail.com", "username": "gnaygnil"}]}, "pending_reviewers": {}, "reviewer_updates": [{"updated": "2022-09-07 02:30:07.000000000", "updated_by": {"_account_id": 1000855, "name": "Jenkins", "username": "ci", "tags": ["SERVICE_USER"]}, "reviewer": {"_account_id": 1000855, "name": "Jenkins", "username": "ci", "tags": ["SERVICE_USER"]}, "state": "CC"}, {"updated": "2022-09-07 03:13:56.000000000", "updated_by": {"_account_id": 1000855, "name": "Jenkins", "username": "ci", "tags": ["SERVICE_USER"]}, "reviewer": {"_account_id": 1000855, "name": "Jenkins", "username": "ci", "tags": ["SERVICE_USER"]}, "state": "REVIEWER"}, {"updated": "2022-09-07 03:56:23.000000000", "updated_by": {"_account_id": 1001371, "name": "Review bot", "username": "pootlebot", "status": "🤖", "tags": ["SERVICE_USER"]}, "reviewer": {"_account_id": 1000006, "name": "Thorsten Behrens", "email": "thorsten.behrens@collabora.com", "username": "thb"}, "state": "REVIEWER"}, {"updated": "2022-09-07 03:56:23.000000000", "updated_by": {"_account_id": 1001371, "name": "Review bot", "username": "pootlebot", "status": "🤖", "tags": ["SERVICE_USER"]}, "reviewer": {"_account_id": 1001371, "name": "Review bot", "username": "pootlebot", "status": "🤖", "tags": ["SERVICE_USER"]}, "state": "CC"}, {"updated": "2022-09-13 06:37:26.000000000", "updated_by": {"_account_id": 1000130, "name": "René Engelhard", "email": "rene@debian.org", "username": "rene"}, "reviewer": {"_account_id": 1000130, "name": "René Engelhard", "email": "rene@debian.org", "username": "rene"}, "state": "REVIEWER"}, {"updated": "2022-10-14 09:51:30.000000000", "updated_by": {"_account_id": 1000083, "name": "Noel Grandin", "email": "noel.grandin@collabora.co.uk", "username": "grandinj"}, "reviewer": {"_account_id": 1000083, "name": "Noel Grandin", "email": "noel.grandin@collabora.co.uk", "username": "grandinj"}, "state": "CC"}, {"updated": "2023-01-26 15:15:33.000000000", "updated_by": {"_account_id": 1000022, "name": "Michael Stahl", "email": "michael.stahl@collabora.com", "username": "mst", "status": "🦥"}, "reviewer": {"_account_id": 1000022, "name": "Michael Stahl", "email": "michael.stahl@collabora.com", "username": "mst", "status": "🦥"}, "state": "REVIEWER"}], "messages": [{"id": "ec7be7b2196e9fe3994d1d48461a917364df8b76", "tag": "autogenerated:gerrit:newPatchSet", "author": {"_account_id": 1003709, "name": "Gnil Gnay", "display_name": "Ling Yang", "email": "gnaygnil@gmail.com", "username": "gnaygnil"}, "date": "2022-09-07 02:29:46.000000000", "message": "Uploaded patch set 1.", "accounts_in_message": [], "_revision_number": 1}, {"id": "fbe0547b3e2305a5236d4b36f64bfca629458896", "author": {"_account_id": 1000855, "name": "Jenkins", "username": "ci", "tags": ["SERVICE_USER"]}, "date": "2022-09-07 02:30:07.000000000", "message": "Patch Set 1:\n\nBuild queued https://ci.libreoffice.org/job/gerrit_master/122202/", "accounts_in_message": [], "_revision_number": 1}, {"id": "e6fe8c65b4cdeb5a4f7699ec06c241f044e8e4e1", "author": {"_account_id": 1000855, "name": "Jenkins", "username": "ci", "tags": ["SERVICE_USER"]}, "date": "2022-09-07 03:13:56.000000000", "message": "Patch Set 1: Verified+1\n\nBuild Successful \n\nhttps://ci.libreoffice.org/job/gerrit_master/122202/ : SUCCESS", "accounts_in_message": [], "_revision_number": 1}, {"id": "bb9257430c6d66904a7c353d552220be1f3e67c6", "author": {"_account_id": 1001371, "name": "Review bot", "username": "pootlebot", "status": "🤖", "tags": ["SERVICE_USER"]}, "date": "2022-09-07 03:56:23.000000000", "message": "Patch Set 1:\n\nadded reviewer", "accounts_in_message": [], "_revision_number": 1}, {"id": "0269f1cbb9059deb88960a293479a00710ee7140", "author": {"_account_id": 1003709, "name": "Gnil Gnay", "display_name": "Ling Yang", "email": "gnaygnil@gmail.com", "username": "gnaygnil"}, "date": "2022-09-13 03:56:39.000000000", "message": "Patch Set 1: Code-Review+1", "accounts_in_message": [], "_revision_number": 1}, {"id": "da02ce480c373a0e2bff38d3f65c7c9aa5d4ca92", "author": {"_account_id": 1000130, "name": "René Engelhard", "email": "rene@debian.org", "username": "rene"}, "date": "2022-09-13 06:37:26.000000000", "message": "Patch Set 1: Code-Review+1", "accounts_in_message": [], "_revision_number": 1}, {"id": "82943555c652a9886843135345132b50a602424c", "author": {"_account_id": 1001371, "name": "Review bot", "username": "pootlebot", "status": "🤖", "tags": ["SERVICE_USER"]}, "date": "2022-10-14 03:31:25.000000000", "message": "Patch Set 1:\n\nA polite ping, still working on this patch? Do not forget to rebase it first. See https://wiki.documentfoundation.org/Development/Review_bot", "accounts_in_message": [], "_revision_number": 1}, {"id": "3cba64d8c2b9c213cdaee3454fd9937c4b98d1ed", "author": {"_account_id": 1000083, "name": "Noel Grandin", "email": "noel.grandin@collabora.co.uk", "username": "grandinj"}, "date": "2022-10-14 09:51:30.000000000", "message": "Patch Set 1:\n\n(1 comment)", "accounts_in_message": [], "_revision_number": 1}, {"id": "ac37c2175d493e5bab01623c6493d1f6b6dbccc1", "author": {"_account_id": 1001371, "name": "Review bot", "username": "pootlebot", "status": "🤖", "tags": ["SERVICE_USER"]}, "date": "2022-11-14 03:30:30.000000000", "message": "Patch Set 1:\n\nA polite ping, still working on this patch? Do not forget to rebase it first. See https://wiki.documentfoundation.org/Development/Review_bot", "accounts_in_message": [], "_revision_number": 1}, {"id": "7c641ea91290745cc67d82097571057b1b476fe8", "author": {"_account_id": 1000006, "name": "Thorsten Behrens", "email": "thorsten.behrens@collabora.com", "username": "thb"}, "date": "2022-11-23 16:04:02.000000000", "message": "Patch Set 1:\n\n(1 comment)", "accounts_in_message": [], "_revision_number": 1}, {"id": "2368d47cda597371723e1c63169079632e371471", "author": {"_account_id": 1001371, "name": "Review bot", "username": "pootlebot", "status": "🤖", "tags": ["SERVICE_USER"]}, "date": "2022-12-24 03:24:25.000000000", "message": "Patch Set 1:\n\nA polite ping, still working on this patch? Do not forget to rebase it first. See https://wiki.documentfoundation.org/Development/Review_bot", "accounts_in_message": [], "_revision_number": 1}, {"id": "81eec05357b5d84aa3a74d188cc7280669b65a86", "tag": "autogenerated:gerrit:abandon", "author": {"_account_id": 1001371, "name": "Review bot", "username": "pootlebot", "status": "🤖", "tags": ["SERVICE_USER"]}, "date": "2023-01-24 03:19:12.000000000", "message": "Abandoned\n\nAbandoning this for the moment due to inactivity. Be aware it can be reopened anytime if you still want to continue working on it. Do not forget to rebase it first. See https://wiki.documentfoundation.org/Development/Review_bot", "accounts_in_message": [], "_revision_number": 1}, {"id": "59859b5740eb73ae8e754563d6e7e1f1f5123858", "tag": "autogenerated:gerrit:restore", "author": {"_account_id": 1000022, "name": "Michael Stahl", "email": "michael.stahl@collabora.com", "username": "mst", "status": "🦥"}, "date": "2023-01-26 15:11:05.000000000", "message": "Restored", "accounts_in_message": [], "_revision_number": 1}, {"id": "8d7d5d803233ae27453c7a1684bbe03a289f66c0", "tag": "autogenerated:gerrit:newPatchSet", "author": {"_account_id": 1000022, "name": "Michael Stahl", "email": "michael.stahl@collabora.com", "username": "mst", "status": "🦥"}, "date": "2023-01-26 15:13:35.000000000", "message": "Uploaded patch set 2.", "accounts_in_message": [], "_revision_number": 2}, {"id": "6956260fd420c98f7ae96150392cbc222592f9b6", "author": {"_account_id": 1000855, "name": "Jenkins", "username": "ci", "tags": ["SERVICE_USER"]}, "date": "2023-01-26 15:13:53.000000000", "message": "Patch Set 2:\n\nBuild queued https://ci.libreoffice.org/job/gerrit_master/131854/", "accounts_in_message": [], "_revision_number": 2}, {"id": "03bf2e48fce0b6ae63f04a141bca2712a4b7ecb6", "author": {"_account_id": 1000022, "name": "Michael Stahl", "email": "michael.stahl@collabora.com", "username": "mst", "status": "🦥"}, "date": "2023-01-26 15:15:33.000000000", "message": "Patch Set 2: Code-Review+2\n\n(1 comment)", "accounts_in_message": [], "_revision_number": 2}, {"id": "9e9d2239f6c47c34cecf8e4b6cca14b006446098", "author": {"_account_id": 1000855, "name": "Jenkins", "username": "ci", "tags": ["SERVICE_USER"]}, "date": "2023-01-26 16:42:59.000000000", "message": "Patch Set 2: Verified+1\n\nBuild Successful \n\nhttps://ci.libreoffice.org/job/gerrit_master/131854/ : SUCCESS", "accounts_in_message": [], "_revision_number": 2}, {"id": "879c4d9d79c8ef93a013425aaaa83a13706c90cb", "tag": "autogenerated:gerrit:merged", "author": {"_account_id": 1000022, "name": "Michael Stahl", "email": "michael.stahl@collabora.com", "username": "mst", "status": "🦥"}, "date": "2023-01-26 16:45:19.000000000", "message": "Change has been successfully cherry-picked as a03dbcf786481d7b9294354399c83b46972ac85a", "accounts_in_message": [], "_revision_number": 3}], "current_revision_number": 3, "current_revision": "a03dbcf786481d7b9294354399c83b46972ac85a", "revisions": {"fd2282dec76932670c9d5db47334d209294da942": {"kind": "REWORK", "_number": 1, "created": "2022-09-07 02:29:46.000000000", "uploader": {"_account_id": 1003709, "name": "Gnil Gnay", "display_name": "Ling Yang", "email": "gnaygnil@gmail.com", "username": "gnaygnil"}, "ref": "refs/changes/49/139549/1", "fetch": {"anonymous http": {"url": "https://git.libreoffice.org/core", "ref": "refs/changes/49/139549/1"}}, "branch": "refs/heads/master"}, "7703ff8a2e6edd00b6d5bc189c18d8d8efd1799a": {"kind": "REWORK", "_number": 2, "created": "2023-01-26 15:13:35.000000000", "uploader": {"_account_id": 1000022, "name": "Michael Stahl", "email": "michael.stahl@collabora.com", "username": "mst", "status": "🦥"}, "ref": "refs/changes/49/139549/2", "fetch": {"anonymous http": {"url": "https://git.libreoffice.org/core", "ref": "refs/changes/49/139549/2"}}, "branch": "refs/heads/master"}, "a03dbcf786481d7b9294354399c83b46972ac85a": {"kind": "REWORK", "_number": 3, "created": "2023-01-26 16:45:19.000000000", "uploader": {"_account_id": 1000022, "name": "Michael Stahl", "email": "michael.stahl@collabora.com", "username": "mst", "status": "🦥"}, "ref": "refs/changes/49/139549/3", "fetch": {"anonymous http": {"url": "https://git.libreoffice.org/core", "ref": "refs/changes/49/139549/3"}}, "branch": "refs/heads/master"}}, "requirements": [], "submit_records": [{"rule_name": "gerrit~PrologRule", "status": "CLOSED", "labels": [{"label": "Code-Review", "status": "OK", "applied_by": {"_account_id": 1000022, "name": "Michael Stahl", "email": "michael.stahl@collabora.com", "username": "mst", "status": "🦥"}}, {"label": "Verified", "status": "OK", "applied_by": {"_account_id": 1000855, "name": "Jenkins", "username": "ci", "tags": ["SERVICE_USER"]}}]}]}